.testr.conf
.travis.yml
Makefile
README.md
circle.yml
requirements.txt
setup.cfg
setup.py
test-requirements.txt
tox.ini
libindic/payyans/__init__.py
libindic/payyans/core.py
libindic/payyans/expose.py
libindic/payyans/maps/ambili.map
libindic/payyans/maps/banglapedia.map
libindic/payyans/maps/charaka.map
libindic/payyans/maps/haritha.map
libindic/payyans/maps/indulekha.map
libindic/payyans/maps/karthika.map
libindic/payyans/maps/manorama.map
libindic/payyans/maps/matweb.map
libindic/payyans/maps/nandini.map
libindic/payyans/maps/panchari.map
libindic/payyans/maps/revathi.map
libindic/payyans/maps/template.map
libindic/payyans/maps/uma.map
libindic/payyans/maps/valluvar.map
libindic/payyans/templates/libindic.payyans.html
libindic/payyans/tests/__init__.py
libindic/payyans/tests/test_payyans.py
libindic_payyans.egg-info/PKG-INFO
libindic_payyans.egg-info/SOURCES.txt
libindic_payyans.egg-info/dependency_links.txt
libindic_payyans.egg-info/namespace_packages.txt
libindic_payyans.egg-info/not-zip-safe
libindic_payyans.egg-info/pbr.json
libindic_payyans.egg-info/top_level.txt